{
  "applications": "*",
  "changelogDate": "20220126184943",
  "dto": "mapstruct",
  "embedded": false,
  "entityTableName": "course_level",
  "fields": [
    {
      "fieldName": "id",
      "fieldType": "Long",
      "fieldValidateRules": ["required"]
    },
    {
      "fieldName": "title",
      "fieldType": "String",
      "fieldValidateRules": ["minlength", "maxlength"],
      "fieldValidateRulesMaxlength": "50",
      "fieldValidateRulesMinlength": "10"
    },
    {
      "fieldName": "description",
      "fieldType": "String",
      "fieldValidateRules": ["minlength", "maxlength"],
      "fieldValidateRulesMaxlength": "400",
      "fieldValidateRulesMinlength": "10"
    }
  ],
  "fluentMethods": true,
  "jpaMetamodelFiltering": true,
  "name": "CourseLevel",
  "pagination": "pagination",
  "readOnly": false,
  "relationships": [],
  "service": "serviceImpl"
}
